sniptext/__init__.py
sniptext/app.py
sniptext/cli.py
sniptext/ocr.py
sniptext-1.0.0.dist-info/licenses/LICENSE
sniptext-1.0.0.dist-info/METADATA
sniptext-1.0.0.dist-info/WHEEL
sniptext-1.0.0.dist-info/entry_points.txt
sniptext-1.0.0.dist-info/top_level.txt
sniptext-1.0.0.dist-info/RECORD
