Metadata-Version: 2.4
Name: sniptext
Version: 1.0.0
Summary: A screenshot tool that automatically copies extracted text to clipboard
Home-page: https://github.com/aadityakanjolia4
Author: Aaditya Kanjolia
Author-email: Aaditya Kanjolia <a21kanjolia@gmail.com>
License: MIT
Project-URL: Homepage, https://github.com/aadityakanjolia4
Keywords: screenshot,ocr,clipboard,text-extraction,desktop-tool
Classifier: Development Status :: 4 - Beta
Classifier: Intended Audience :: End Users/Desktop
Classifier: License :: OSI Approved :: MIT License
Classifier: Operating System :: OS Independent
Classifier: Programming Language :: Python :: 3
Classifier: Programming Language :: Python :: 3.7
Classifier: Programming Language :: Python :: 3.8
Classifier: Programming Language :: Python :: 3.9
Classifier: Programming Language :: Python :: 3.10
Classifier: Programming Language :: Python :: 3.11
Classifier: Topic :: Multimedia :: Graphics :: Capture :: Screen Capture
Classifier: Topic :: Text Processing
Classifier: Topic :: Utilities
Requires-Python: >=3.7
License-File: LICENSE
Requires-Dist: PyQt5>=5.15.0
Requires-Dist: rapidocr-onnxruntime>=1.3.0
Requires-Dist: numpy>=1.21.0
Requires-Dist: Pillow>=8.3.0
Dynamic: author
Dynamic: home-page
Dynamic: license-file
Dynamic: requires-python
